tiledbsc/__init__.py
tiledbsc/_version.py
tiledbsc/annotation_dataframe.py
tiledbsc/annotation_matrix.py
tiledbsc/annotation_matrix_group.py
tiledbsc/annotation_pairwise_matrix_group.py
tiledbsc/assay_matrix.py
tiledbsc/assay_matrix_group.py
tiledbsc/io.py
tiledbsc/logging.py
tiledbsc/raw_group.py
tiledbsc/soma.py
tiledbsc/soma_collection.py
tiledbsc/soma_options.py
tiledbsc/soma_slice.py
tiledbsc/tiledb_array.py
tiledbsc/tiledb_group.py
tiledbsc/tiledb_object.py
tiledbsc/types.py
tiledbsc/uns_array.py
tiledbsc/uns_group.py
tiledbsc/util.py
tiledbsc/util_ann.py
tiledbsc/util_tiledb.py
tiledbsc-0.1.11.dist-info/METADATA
tiledbsc-0.1.11.dist-info/WHEEL
tiledbsc-0.1.11.dist-info/top_level.txt
tiledbsc-0.1.11.dist-info/RECORD
