Metadata-Version: 2.1
Name: tiledbsc
Version: 0.1.11
Summary: Python API for efficient storage and retrieval of single-cell data using TileDB
Home-page: https://github.com/single-cell-data/TileDB-SingleCell/apis/python
Author: TileDB, Inc.
Author-email: help@tiledb.io
Maintainer: TileDB, Inc.
Maintainer-email: help@tiledb.io
License: MIT
Classifier: Intended Audience :: Developers
Classifier: Intended Audience :: Information Technology
Classifier: Intended Audience :: Science/Research
Classifier: License :: OSI Approved :: MIT License
Classifier: Programming Language :: Python
Classifier: Topic :: Scientific/Engineering :: Bio-Informatics
Classifier: Operating System :: Unix
Classifier: Operating System :: POSIX :: Linux
Classifier: Operating System :: MacOS :: MacOS X
Classifier: Programming Language :: Python :: 3.7
Classifier: Programming Language :: Python :: 3.8
Classifier: Programming Language :: Python :: 3.9
Requires-Python: >=3.7
Requires-Dist: anndata
Requires-Dist: pandas
Requires-Dist: pyarrow
Requires-Dist: scanpy
Requires-Dist: scipy
Requires-Dist: tiledb (>=0.17.0)
Provides-Extra: dev
Requires-Dist: black ; extra == 'dev'
Requires-Dist: flake8-bugbear ; extra == 'dev'
Requires-Dist: isort ; extra == 'dev'
Requires-Dist: pytest ; extra == 'dev'
Requires-Dist: typeguard ; extra == 'dev'
